djangocms_equation/__init__.py
djangocms_equation/cms_plugins.py
djangocms_equation/forms.py
djangocms_equation/models.py
djangocms_equation/settings.py
djangocms_equation/migrations/0001_initial.py
djangocms_equation/migrations/__init__.py
djangocms_equation/static/djangocms_equation/css/KaTeX_AMS-Regular.2b99a24c.woff
djangocms_equation/static/djangocms_equation/css/KaTeX_AMS-Regular.f9268291.woff2
djangocms_equation/static/djangocms_equation/css/KaTeX_AMS-Regular.fa69c335.ttf
djangocms_equation/static/djangocms_equation/css/KaTeX_Caligraphic-Bold.1236ed57.woff
djangocms_equation/static/djangocms_equation/css/KaTeX_Caligraphic-Bold.a7ffe886.woff2
djangocms_equation/static/djangocms_equation/css/KaTeX_Caligraphic-Bold.f5d35eb9.ttf
djangocms_equation/static/djangocms_equation/css/KaTeX_Caligraphic-Regular.36d89dce.woff2
djangocms_equation/static/djangocms_equation/css/KaTeX_Caligraphic-Regular.99d4f6a4.woff
djangocms_equation/static/djangocms_equation/css/KaTeX_Caligraphic-Regular.d585d0a0.ttf
djangocms_equation/static/djangocms_equation/css/KaTeX_Fraktur-Bold.4087174f.woff2
djangocms_equation/static/djangocms_equation/css/KaTeX_Fraktur-Bold.9cec01aa.woff
djangocms_equation/static/djangocms_equation/css/KaTeX_Fraktur-Bold.add72209.ttf
djangocms_equation/static/djangocms_equation/css/KaTeX_Fraktur-Regular.590ccc44.ttf
djangocms_equation/static/djangocms_equation/css/KaTeX_Fraktur-Regular.94c6c56c.woff
djangocms_equation/static/djangocms_equation/css/KaTeX_Fraktur-Regular.dc4e9342.woff2
djangocms_equation/static/djangocms_equation/css/KaTeX_Main-Bold.012da1b1.ttf
djangocms_equation/static/djangocms_equation/css/KaTeX_Main-Bold.cd8fffcf.woff2
djangocms_equation/static/djangocms_equation/css/KaTeX_Main-Bold.f1a41613.woff
djangocms_equation/static/djangocms_equation/css/KaTeX_Main-BoldItalic.22b9e5c6.woff2
djangocms_equation/static/djangocms_equation/css/KaTeX_Main-BoldItalic.44567f4c.woff
djangocms_equation-0.2.4.dist-info/AUTHORS.rst
djangocms_equation-0.2.4.dist-info/LICENSE
djangocms_equation-0.2.4.dist-info/METADATA
djangocms_equation-0.2.4.dist-info/WHEEL
djangocms_equation-0.2.4.dist-info/top_level.txt
djangocms_equation-0.2.4.dist-info/RECORD
