Metadata-Version: 2.1
Name: djangocms-equation
Version: 0.2.4
Summary: DjangoCMS plugin to write equations, utilizing KaTeX
Home-page: https://github.com/s-weigand/djangocms-equation
Author: Sebastian Weigand
Author-email: s.weigand.phy@gmail.com
License: Apache Software License 2.0
Project-URL: Documentation, https://djangocms-equation.readthedocs.io/
Project-URL: Source, https://github.com/s-weigand/djangocms-equation
Project-URL: Tracker, https://github.com/s-weigand/djangocms-equation/issues
Project-URL: Changelog, https://djangocms-equation.readthedocs.io/en/latest/history.html
Keywords: djangocms-equation django-cms django cms equation latex katex mhchem
Platform: UNKNOWN
Classifier: Development Status :: 2 - Pre-Alpha
Classifier: Intended Audience :: Developers
Classifier: License :: OSI Approved :: Apache Software License
Classifier: Natural Language :: English
Classifier: Environment :: Web Environment
Classifier: Framework :: Django
Classifier: Framework :: Django :: 1.11
Classifier: Framework :: Django :: 2.1
Classifier: Framework :: Django :: 2.2
Classifier: Framework :: Django CMS :: 3.4
Classifier: Framework :: Django CMS :: 3.5
Classifier: Framework :: Django CMS :: 3.6
Classifier: Framework :: Django CMS :: 3.7
Classifier: Intended Audience :: Developers
Classifier: Operating System :: OS Independent
Classifier: Topic :: Communications
Classifier: Topic :: Internet :: WWW/HTTP :: Dynamic Content
Classifier: Topic :: Internet :: WWW/HTTP :: Dynamic Content :: Message Boards
Classifier: Programming Language :: Python :: 3
Classifier: Programming Language :: Python :: 3.6
Classifier: Programming Language :: Python :: 3.7
Classifier: Programming Language :: Python :: 3.8
Classifier: Programming Language :: Python :: 3.9
Requires-Python: >=3.6
